pwtgbot/__init__.py
pwtgbot/__main__.py
pwtgbot/pwtgbot.py
pwtgbot-1.2.3.dist-info/LICENSE
pwtgbot-1.2.3.dist-info/METADATA
pwtgbot-1.2.3.dist-info/WHEEL
pwtgbot-1.2.3.dist-info/entry_points.txt
pwtgbot-1.2.3.dist-info/top_level.txt
pwtgbot-1.2.3.dist-info/RECORD
