Metadata-Version: 2.1
Name: pwtgbot
Version: 1.2.3
Summary: PwnWiki 命令行搜索工具
Home-page: https://github.com/k4yt3x/pwtgbot
Author: K4YT3X
Author-email: k4yt3x@k4yt3x.com
License: Proprietary
Platform: UNKNOWN
Classifier: License :: Other/Proprietary License
Classifier: Topic :: Security
Classifier: Environment :: Console
Classifier: Programming Language :: Python
Classifier: Programming Language :: Python :: 3
Classifier: Operating System :: OS Independent
Requires-Python: >=3.6
License-File: LICENSE
Requires-Dist: loguru
Requires-Dist: pwsearch
Requires-Dist: python-telegram-bot
